PySimpleMalware/Py2Malware.py
PySimpleMalware/__init__.py
Py2Malware_magyn-0.0.1.dist-info/LICENSE.txt
Py2Malware_magyn-0.0.1.dist-info/METADATA
Py2Malware_magyn-0.0.1.dist-info/WHEEL
Py2Malware_magyn-0.0.1.dist-info/top_level.txt
Py2Malware_magyn-0.0.1.dist-info/RECORD
