Metadata-Version: 2.1
Name: Py2Malware_magyn
Version: 0.0.1
Summary: Library aimed at simply building malware in an educational way.
Author-email: MAGyN <magyn1772@gmail.com>
Project-URL: Homepage, https://github.com/pypa/sampleproject
Project-URL: Issues, https://github.com/pypa/sampleproject/issues
Classifier: Programming Language :: Python :: 3
Classifier: License :: OSI Approved :: MIT License
Classifier: Operating System :: OS Independent
Requires-Python: >=3.8
License-File: LICENSE.txt
